Metadata-Version: 2.1
Name: ghostbusterV2
Version: 0.0.8
Summary: Eliminate dangling elastic IPs by performing analysis on your resources within all your AWS accounts.
Home-page: https://github.com/yash2999/ghostbuster
Author: yash2999
Author-email: bharadwajyash11@gmail.com
License: Apache Software License 2.0
Platform: UNKNOWN
Classifier: Development Status :: 3 - Alpha
Classifier: Intended Audience :: Developers
Classifier: Topic :: Software Development :: Libraries
Classifier: License :: OSI Approved :: GNU Affero General Public License v3
Classifier: Programming Language :: Python :: 3.8
Requires-Python: >=0.0.1
License-File: LICENSE
